setup.py
pyprofilr/__init__.py
pyprofilr/profile.py
pyprofilr.egg-info/PKG-INFO
pyprofilr.egg-info/SOURCES.txt
pyprofilr.egg-info/dependency_links.txt
pyprofilr.egg-info/not-zip-safe
pyprofilr.egg-info/top_level.txt