Metadata-Version: 1.0
Name: pyprofilr
Version: 0.1
Summary: Profile data in Python
Home-page: http://github.com/paulhendricks/pyprofilr
Author: Paul Hendricks
Author-email: paul.hendricks.2013@owu.edu
License: MIT
Platform: UNKNOWN
